tvml/__init__.py
tvml/dsworker.py
tvml/mongostats.py
tvml/predict.py
tvml-0.1.6.7.dist-info/LICENSE
tvml-0.1.6.7.dist-info/METADATA
tvml-0.1.6.7.dist-info/WHEEL
tvml-0.1.6.7.dist-info/top_level.txt
tvml-0.1.6.7.dist-info/RECORD
