Metadata-Version: 2.1
Name: tvml
Version: 0.1.6.7
Summary: Package for everything
Home-page: https://github.com/trendvision/tvmlopen
Author: Pazlvbanke
Author-email: pazlvbanke@yandex.ru
License: UNKNOWN
Platform: UNKNOWN
Classifier: Programming Language :: Python :: 3
Classifier: License :: OSI Approved :: MIT License
Classifier: Operating System :: OS Independent
Requires-Dist: boto3
Requires-Dist: mlflow
